CHANGES.rst
LICENSE.md
MANIFEST.in
README.rst
requirements-dev.txt
requirements.txt
setup.py
django_google_address.egg-info/PKG-INFO
django_google_address.egg-info/SOURCES.txt
django_google_address.egg-info/dependency_links.txt
django_google_address.egg-info/not-zip-safe
django_google_address.egg-info/requires.txt
django_google_address.egg-info/top_level.txt
google_address/__init__.py
google_address/admin.py
google_address/api.py
google_address/apps.py
google_address/helpers.py
google_address/models.py
google_address/signals.py
google_address/update.py
google_address/__pycache__/__init__.cpython-35.pyc
google_address/__pycache__/admin.cpython-35.pyc
google_address/__pycache__/api.cpython-35.pyc
google_address/__pycache__/apps.cpython-35.pyc
google_address/__pycache__/google_address.cpython-35.pyc
google_address/__pycache__/helpers.cpython-35.pyc
google_address/__pycache__/models.cpython-35.pyc
google_address/__pycache__/serializers.cpython-35.pyc
google_address/__pycache__/signals.cpython-35.pyc
google_address/__pycache__/update.cpython-35.pyc
google_address/__pycache__/urls.cpython-35.pyc
google_address/migrations/0001_initial.py
google_address/migrations/0002_auto_20170417_2307.py
google_address/migrations/0003_auto_20170417_2356.py
google_address/migrations/0004_auto_20170418_0133.py
google_address/migrations/0005_auto_20170418_2304.py
google_address/migrations/__init__.py
google_address/migrations/__pycache__/0001_initial.cpython-35.pyc
google_address/migrations/__pycache__/0002_auto_20170417_2307.cpython-35.pyc
google_address/migrations/__pycache__/0003_auto_20170417_2356.cpython-35.pyc
google_address/migrations/__pycache__/0004_auto_20170418_0133.cpython-35.pyc
google_address/migrations/__pycache__/0005_auto_20170418_2304.cpython-35.pyc
google_address/migrations/__pycache__/__init__.cpython-35.pyc
google_address/tests/__init__.py
google_address/tests/runtests.py
google_address/tests/test_api.py
google_address/tests/test_execution.py
google_address/tests/test_models.py
google_address/tests/test_signals.py
google_address/tests/__pycache__/__init__.cpython-35.pyc
google_address/tests/__pycache__/test_api.cpython-35.pyc
google_address/tests/__pycache__/test_execution.cpython-35.pyc
