Metadata-Version: 1.1
Name: django-google-address
Version: 1.1.0
Summary: UNKNOWN
Home-page: https://github.com/leonardoarroyo/django-google-address
Author: Leonardo Arroyo
Author-email: contato@leonardoarroyo.com
License: MIT
Download-URL: https://github.com/leonardoarroyo/django-google-address/tarball/1.1.0
Platform: UNKNOWN
